salable/__init__.py
salable/client.py
salable/exceptions.py
salable-0.0.4.dist-info/METADATA
salable-0.0.4.dist-info/WHEEL
salable-0.0.4.dist-info/top_level.txt
salable-0.0.4.dist-info/RECORD
